{"nodes": [{"id": "d_codes_image2pdf_src_app_services_pdf_service_ts", "label": "pdf.service.ts", "file_type": "code", "source_file": "D:\\Codes\\image2pdf\\src\\app\\services\\pdf.service.ts", "source_location": "L1"}, {"id": "services_pdf_service_pdfpagesize", "label": "PDFPageSize", "file_type": "code", "source_file": "D:\\Codes\\image2pdf\\src\\app\\services\\pdf.service.ts", "source_location": "L14"}, {"id": "services_pdf_service_pdforientation", "label": "PDFOrientation", "file_type": "code", "source_file": "D:\\Codes\\image2pdf\\src\\app\\services\\pdf.service.ts", "source_location": "L15"}, {"id": "services_pdf_service_pdfquality", "label": "PDFQuality", "file_type": "code", "source_file": "D:\\Codes\\image2pdf\\src\\app\\services\\pdf.service.ts", "source_location": "L16"}, {"id": "services_pdf_service_pdfimagefit", "label": "PDFImageFit", "file_type": "code", "source_file": "D:\\Codes\\image2pdf\\src\\app\\services\\pdf.service.ts", "source_location": "L17"}, {"id": "services_pdf_service_pdfimagealignment", "label": "PDFImageAlignment", "file_type": "code", "source_file": "D:\\Codes\\image2pdf\\src\\app\\services\\pdf.service.ts", "source_location": "L18"}, {"id": "services_pdf_service_pdfimagesperpage", "label": "PDFImagesPerPage", "file_type": "code", "source_file": "D:\\Codes\\image2pdf\\src\\app\\services\\pdf.service.ts", "source_location": "L19"}, {"id": "services_pdf_service_pdfsettings", "label": "PDFSettings", "file_type": "code", "source_file": "D:\\Codes\\image2pdf\\src\\app\\services\\pdf.service.ts", "source_location": "L21"}, {"id": "services_pdf_service_resolvedpdfsettings", "label": "ResolvedPDFSettings", "file_type": "code", "source_file": "D:\\Codes\\image2pdf\\src\\app\\services\\pdf.service.ts", "source_location": "L35"}, {"id": "services_pdf_service_pdfservice", "label": "PDFService", "file_type": "code", "source_file": "D:\\Codes\\image2pdf\\src\\app\\services\\pdf.service.ts", "source_location": "L52"}, {"id": "services_pdf_service_pdfservice_constructor", "label": ".constructor()", "file_type": "code", "source_file": "D:\\Codes\\image2pdf\\src\\app\\services\\pdf.service.ts", "source_location": "L53"}, {"id": "services_pdf_service_pdfservice_generatepdf", "label": ".generatePDF()", "file_type": "code", "source_file": "D:\\Codes\\image2pdf\\src\\app\\services\\pdf.service.ts", "source_location": "L58"}, {"id": "services_pdf_service_pdfservice_createpdfblob", "label": ".createPDFBlob()", "file_type": "code", "source_file": "D:\\Codes\\image2pdf\\src\\app\\services\\pdf.service.ts", "source_location": "L108"}, {"id": "services_pdf_service_pdfservice_createpdf", "label": ".createPDF()", "file_type": "code", "source_file": "D:\\Codes\\image2pdf\\src\\app\\services\\pdf.service.ts", "source_location": "L135"}, {"id": "services_pdf_service_pdfservice_resolvesettings", "label": ".resolveSettings()", "file_type": "code", "source_file": "D:\\Codes\\image2pdf\\src\\app\\services\\pdf.service.ts", "source_location": "L217"}, {"id": "services_pdf_service_pdfservice_coercemargin", "label": ".coerceMargin()", "file_type": "code", "source_file": "D:\\Codes\\image2pdf\\src\\app\\services\\pdf.service.ts", "source_location": "L233"}, {"id": "services_pdf_service_pdfservice_coercehexcolor", "label": ".coerceHexColor()", "file_type": "code", "source_file": "D:\\Codes\\image2pdf\\src\\app\\services\\pdf.service.ts", "source_location": "L238"}, {"id": "services_pdf_service_pdfservice_fillpagebackground", "label": ".fillPageBackground()", "file_type": "code", "source_file": "D:\\Codes\\image2pdf\\src\\app\\services\\pdf.service.ts", "source_location": "L242"}, {"id": "services_pdf_service_pdfservice_addimagetocell", "label": ".addImageToCell()", "file_type": "code", "source_file": "D:\\Codes\\image2pdf\\src\\app\\services\\pdf.service.ts", "source_location": "L247"}], "edges": [{"source": "d_codes_image2pdf_src_app_services_pdf_service_ts", "target": "core", "relation": "imports_from", "context": "import", "confidence": "EXTRACTED", "source_file": "D:\\Codes\\image2pdf\\src\\app\\services\\pdf.service.ts", "source_location": "L1", "weight": 1.0}, {"source": "d_codes_image2pdf_src_app_services_pdf_service_ts", "target": "jspdf", "relation": "imports_from", "context": "import", "confidence": "EXTRACTED", "source_file": "D:\\Codes\\image2pdf\\src\\app\\services\\pdf.service.ts", "source_location": "L2", "weight": 1.0}, {"source": "d_codes_image2pdf_src_app_services_pdf_service_ts", "target": "d_codes_image2pdf_src_app_services_file_service_ts", "relation": "imports_from", "context": "import", "confidence": "EXTRACTED", "source_file": "D:\\Codes\\image2pdf\\src\\app\\services\\pdf.service.ts", "source_location": "L3", "weight": 1.0}, {"source": "d_codes_image2pdf_src_app_services_pdf_service_ts", "target": "services_file_service_fileobject", "relation": "imports", "context": "import", "confidence": "EXTRACTED", "source_file": "D:\\Codes\\image2pdf\\src\\app\\services\\pdf.service.ts", "source_location": "L3", "weight": 1.0}, {"source": "d_codes_image2pdf_src_app_services_pdf_service_ts", "target": "d_codes_image2pdf_src_app_services_pdf_worker_service_ts", "relation": "imports_from", "context": "import", "confidence": "EXTRACTED", "source_file": "D:\\Codes\\image2pdf\\src\\app\\services\\pdf.service.ts", "source_location": "L4", "weight": 1.0}, {"source": "d_codes_image2pdf_src_app_services_pdf_service_ts", "target": "services_pdf_worker_service_pdfworkerservice", "relation": "imports", "context": "import", "confidence": "EXTRACTED", "source_file": "D:\\Codes\\image2pdf\\src\\app\\services\\pdf.service.ts", "source_location": "L4", "weight": 1.0}, {"source": "d_codes_image2pdf_src_app_services_pdf_service_ts", "target": "d_codes_image2pdf_src_app_utils_pdf_layout_engine_ts", "relation": "imports_from", "context": "import", "confidence": "EXTRACTED", "source_file": "D:\\Codes\\image2pdf\\src\\app\\services\\pdf.service.ts", "source_location": "L5", "weight": 1.0}, {"source": "d_codes_image2pdf_src_app_services_pdf_service_ts", "target": "utils_pdf_layout_engine_calculatepagelayout", "relation": "imports", "context": "import", "confidence": "EXTRACTED", "source_file": "D:\\Codes\\image2pdf\\src\\app\\services\\pdf.service.ts", "source_location": "L5", "weight": 1.0}, {"source": "d_codes_image2pdf_src_app_services_pdf_service_ts", "target": "utils_pdf_layout_engine_calculateimagedimensions", "relation": "imports", "context": "import", "confidence": "EXTRACTED", "source_file": "D:\\Codes\\image2pdf\\src\\app\\services\\pdf.service.ts", "source_location": "L5", "weight": 1.0}, {"source": "d_codes_image2pdf_src_app_services_pdf_service_ts", "target": "utils_pdf_layout_engine_calculateimageposition", "relation": "imports", "context": "import", "confidence": "EXTRACTED", "source_file": "D:\\Codes\\image2pdf\\src\\app\\services\\pdf.service.ts", "source_location": "L5", "weight": 1.0}, {"source": "d_codes_image2pdf_src_app_services_pdf_service_ts", "target": "utils_pdf_layout_engine_coerceimagesperpage", "relation": "imports", "context": "import", "confidence": "EXTRACTED", "source_file": "D:\\Codes\\image2pdf\\src\\app\\services\\pdf.service.ts", "source_location": "L5", "weight": 1.0}, {"source": "d_codes_image2pdf_src_app_services_pdf_service_ts", "target": "utils_pdf_layout_engine_getorientedpagedimensions", "relation": "imports", "context": "import", "confidence": "EXTRACTED", "source_file": "D:\\Codes\\image2pdf\\src\\app\\services\\pdf.service.ts", "source_location": "L5", "weight": 1.0}, {"source": "d_codes_image2pdf_src_app_services_pdf_service_ts", "target": "utils_pdf_layout_engine_sanitizemargins", "relation": "imports", "context": "import", "confidence": "EXTRACTED", "source_file": "D:\\Codes\\image2pdf\\src\\app\\services\\pdf.service.ts", "source_location": "L5", "weight": 1.0}, {"source": "d_codes_image2pdf_src_app_services_pdf_service_ts", "target": "services_pdf_service_pdfpagesize", "relation": "contains", "confidence": "EXTRACTED", "source_file": "D:\\Codes\\image2pdf\\src\\app\\services\\pdf.service.ts", "source_location": "L14", "weight": 1.0}, {"source": "d_codes_image2pdf_src_app_services_pdf_service_ts", "target": "services_pdf_service_pdforientation", "relation": "contains", "confidence": "EXTRACTED", "source_file": "D:\\Codes\\image2pdf\\src\\app\\services\\pdf.service.ts", "source_location": "L15", "weight": 1.0}, {"source": "d_codes_image2pdf_src_app_services_pdf_service_ts", "target": "services_pdf_service_pdfquality", "relation": "contains", "confidence": "EXTRACTED", "source_file": "D:\\Codes\\image2pdf\\src\\app\\services\\pdf.service.ts", "source_location": "L16", "weight": 1.0}, {"source": "d_codes_image2pdf_src_app_services_pdf_service_ts", "target": "services_pdf_service_pdfimagefit", "relation": "contains", "confidence": "EXTRACTED", "source_file": "D:\\Codes\\image2pdf\\src\\app\\services\\pdf.service.ts", "source_location": "L17", "weight": 1.0}, {"source": "d_codes_image2pdf_src_app_services_pdf_service_ts", "target": "services_pdf_service_pdfimagealignment", "relation": "contains", "confidence": "EXTRACTED", "source_file": "D:\\Codes\\image2pdf\\src\\app\\services\\pdf.service.ts", "source_location": "L18", "weight": 1.0}, {"source": "d_codes_image2pdf_src_app_services_pdf_service_ts", "target": "services_pdf_service_pdfimagesperpage", "relation": "contains", "confidence": "EXTRACTED", "source_file": "D:\\Codes\\image2pdf\\src\\app\\services\\pdf.service.ts", "source_location": "L19", "weight": 1.0}, {"source": "d_codes_image2pdf_src_app_services_pdf_service_ts", "target": "services_pdf_service_pdfsettings", "relation": "contains", "confidence": "EXTRACTED", "source_file": "D:\\Codes\\image2pdf\\src\\app\\services\\pdf.service.ts", "source_location": "L21", "weight": 1.0}, {"source": "d_codes_image2pdf_src_app_services_pdf_service_ts", "target": "services_pdf_service_resolvedpdfsettings", "relation": "contains", "confidence": "EXTRACTED", "source_file": "D:\\Codes\\image2pdf\\src\\app\\services\\pdf.service.ts", "source_location": "L35", "weight": 1.0}, {"source": "d_codes_image2pdf_src_app_services_pdf_service_ts", "target": "services_pdf_service_pdfservice", "relation": "contains", "confidence": "EXTRACTED", "source_file": "D:\\Codes\\image2pdf\\src\\app\\services\\pdf.service.ts", "source_location": "L52", "weight": 1.0}, {"source": "services_pdf_service_pdfservice", "target": "services_pdf_service_pdfservice_constructor", "relation": "method", "confidence": "EXTRACTED", "source_file": "D:\\Codes\\image2pdf\\src\\app\\services\\pdf.service.ts", "source_location": "L53", "weight": 1.0}, {"source": "services_pdf_service_pdfservice", "target": "services_pdf_service_pdfservice_generatepdf", "relation": "method", "confidence": "EXTRACTED", "source_file": "D:\\Codes\\image2pdf\\src\\app\\services\\pdf.service.ts", "source_location": "L58", "weight": 1.0}, {"source": "services_pdf_service_pdfservice", "target": "services_pdf_service_pdfservice_createpdfblob", "relation": "method", "confidence": "EXTRACTED", "source_file": "D:\\Codes\\image2pdf\\src\\app\\services\\pdf.service.ts", "source_location": "L108", "weight": 1.0}, {"source": "services_pdf_service_pdfservice", "target": "services_pdf_service_pdfservice_createpdf", "relation": "method", "confidence": "EXTRACTED", "source_file": "D:\\Codes\\image2pdf\\src\\app\\services\\pdf.service.ts", "source_location": "L135", "weight": 1.0}, {"source": "services_pdf_service_pdfservice", "target": "services_pdf_service_pdfservice_resolvesettings", "relation": "method", "confidence": "EXTRACTED", "source_file": "D:\\Codes\\image2pdf\\src\\app\\services\\pdf.service.ts", "source_location": "L217", "weight": 1.0}, {"source": "services_pdf_service_pdfservice", "target": "services_pdf_service_pdfservice_coercemargin", "relation": "method", "confidence": "EXTRACTED", "source_file": "D:\\Codes\\image2pdf\\src\\app\\services\\pdf.service.ts", "source_location": "L233", "weight": 1.0}, {"source": "services_pdf_service_pdfservice", "target": "services_pdf_service_pdfservice_coercehexcolor", "relation": "method", "confidence": "EXTRACTED", "source_file": "D:\\Codes\\image2pdf\\src\\app\\services\\pdf.service.ts", "source_location": "L238", "weight": 1.0}, {"source": "services_pdf_service_pdfservice", "target": "services_pdf_service_pdfservice_fillpagebackground", "relation": "method", "confidence": "EXTRACTED", "source_file": "D:\\Codes\\image2pdf\\src\\app\\services\\pdf.service.ts", "source_location": "L242", "weight": 1.0}, {"source": "services_pdf_service_pdfservice", "target": "services_pdf_service_pdfservice_addimagetocell", "relation": "method", "confidence": "EXTRACTED", "source_file": "D:\\Codes\\image2pdf\\src\\app\\services\\pdf.service.ts", "source_location": "L247", "weight": 1.0}, {"source": "services_pdf_service_pdfservice_generatepdf", "target": "services_pdf_service_pdfservice_createpdf", "relation": "calls", "context": "call", "confidence": "EXTRACTED", "source_file": "D:\\Codes\\image2pdf\\src\\app\\services\\pdf.service.ts", "source_location": "L100", "weight": 1.0}, {"source": "services_pdf_service_pdfservice_createpdfblob", "target": "services_pdf_service_pdfservice_createpdf", "relation": "calls", "context": "call", "confidence": "EXTRACTED", "source_file": "D:\\Codes\\image2pdf\\src\\app\\services\\pdf.service.ts", "source_location": "L132", "weight": 1.0}, {"source": "services_pdf_service_pdfservice_createpdf", "target": "services_pdf_service_pdfservice_resolvesettings", "relation": "calls", "context": "call", "confidence": "EXTRACTED", "source_file": "D:\\Codes\\image2pdf\\src\\app\\services\\pdf.service.ts", "source_location": "L136", "weight": 1.0}, {"source": "services_pdf_service_pdfservice_createpdf", "target": "services_pdf_service_pdfservice_fillpagebackground", "relation": "calls", "context": "call", "confidence": "EXTRACTED", "source_file": "D:\\Codes\\image2pdf\\src\\app\\services\\pdf.service.ts", "source_location": "L172", "weight": 1.0}, {"source": "services_pdf_service_pdfservice_createpdf", "target": "services_pdf_service_pdfservice_addimagetocell", "relation": "calls", "context": "call", "confidence": "EXTRACTED", "source_file": "D:\\Codes\\image2pdf\\src\\app\\services\\pdf.service.ts", "source_location": "L197", "weight": 1.0}, {"source": "services_pdf_service_pdfservice_resolvesettings", "target": "services_pdf_service_pdfservice_coercemargin", "relation": "calls", "context": "call", "confidence": "EXTRACTED", "source_file": "D:\\Codes\\image2pdf\\src\\app\\services\\pdf.service.ts", "source_location": "L222", "weight": 1.0}, {"source": "services_pdf_service_pdfservice_resolvesettings", "target": "services_pdf_service_pdfservice_coercehexcolor", "relation": "calls", "context": "call", "confidence": "EXTRACTED", "source_file": "D:\\Codes\\image2pdf\\src\\app\\services\\pdf.service.ts", "source_location": "L228", "weight": 1.0}], "raw_calls": [{"caller_nid": "services_pdf_service_pdfservice_generatepdf", "callee": "isWorkerSupported", "is_member_call": true, "source_file": "D:\\Codes\\image2pdf\\src\\app\\services\\pdf.service.ts", "source_location": "L80"}, {"caller_nid": "services_pdf_service_pdfservice_generatepdf", "callee": "map", "is_member_call": true, "source_file": "D:\\Codes\\image2pdf\\src\\app\\services\\pdf.service.ts", "source_location": "L83"}, {"caller_nid": "services_pdf_service_pdfservice_generatepdf", "callee": "error", "is_member_call": true, "source_file": "D:\\Codes\\image2pdf\\src\\app\\services\\pdf.service.ts", "source_location": "L94"}, {"caller_nid": "services_pdf_service_pdfservice_generatepdf", "callee": "save", "is_member_call": true, "source_file": "D:\\Codes\\image2pdf\\src\\app\\services\\pdf.service.ts", "source_location": "L101"}, {"caller_nid": "services_pdf_service_pdfservice_createpdfblob", "callee": "isWorkerSupported", "is_member_call": true, "source_file": "D:\\Codes\\image2pdf\\src\\app\\services\\pdf.service.ts", "source_location": "L114"}, {"caller_nid": "services_pdf_service_pdfservice_createpdfblob", "callee": "generatePDFBlob", "is_member_call": true, "source_file": "D:\\Codes\\image2pdf\\src\\app\\services\\pdf.service.ts", "source_location": "L116"}, {"caller_nid": "services_pdf_service_pdfservice_createpdfblob", "callee": "map", "is_member_call": true, "source_file": "D:\\Codes\\image2pdf\\src\\app\\services\\pdf.service.ts", "source_location": "L117"}, {"caller_nid": "services_pdf_service_pdfservice_createpdfblob", "callee": "error", "is_member_call": true, "source_file": "D:\\Codes\\image2pdf\\src\\app\\services\\pdf.service.ts", "source_location": "L126"}, {"caller_nid": "services_pdf_service_pdfservice_createpdfblob", "callee": "output", "is_member_call": true, "source_file": "D:\\Codes\\image2pdf\\src\\app\\services\\pdf.service.ts", "source_location": "L132"}, {"caller_nid": "services_pdf_service_pdfservice_createpdf", "callee": "getOrientedPageDimensions", "is_member_call": false, "source_file": "D:\\Codes\\image2pdf\\src\\app\\services\\pdf.service.ts", "source_location": "L145"}, {"caller_nid": "services_pdf_service_pdfservice_createpdf", "callee": "sanitizeMargins", "is_member_call": false, "source_file": "D:\\Codes\\image2pdf\\src\\app\\services\\pdf.service.ts", "source_location": "L146"}, {"caller_nid": "services_pdf_service_pdfservice_createpdf", "callee": "calculatePageLayout", "is_member_call": false, "source_file": "D:\\Codes\\image2pdf\\src\\app\\services\\pdf.service.ts", "source_location": "L156"}, {"caller_nid": "services_pdf_service_pdfservice_createpdf", "callee": "addPage", "is_member_call": true, "source_file": "D:\\Codes\\image2pdf\\src\\app\\services\\pdf.service.ts", "source_location": "L169"}, {"caller_nid": "services_pdf_service_pdfservice_createpdf", "callee": "getImageProperties", "is_member_call": true, "source_file": "D:\\Codes\\image2pdf\\src\\app\\services\\pdf.service.ts", "source_location": "L177"}, {"caller_nid": "services_pdf_service_pdfservice_createpdf", "callee": "calculateImageDimensions", "is_member_call": false, "source_file": "D:\\Codes\\image2pdf\\src\\app\\services\\pdf.service.ts", "source_location": "L179"}, {"caller_nid": "services_pdf_service_pdfservice_createpdf", "callee": "calculateImagePosition", "is_member_call": false, "source_file": "D:\\Codes\\image2pdf\\src\\app\\services\\pdf.service.ts", "source_location": "L187"}, {"caller_nid": "services_pdf_service_pdfservice_resolvesettings", "callee": "coerceImagesPerPage", "is_member_call": false, "source_file": "D:\\Codes\\image2pdf\\src\\app\\services\\pdf.service.ts", "source_location": "L229"}, {"caller_nid": "services_pdf_service_pdfservice_coercemargin", "callee": "Number", "is_member_call": false, "source_file": "D:\\Codes\\image2pdf\\src\\app\\services\\pdf.service.ts", "source_location": "L234"}, {"caller_nid": "services_pdf_service_pdfservice_coercemargin", "callee": "isFinite", "is_member_call": true, "source_file": "D:\\Codes\\image2pdf\\src\\app\\services\\pdf.service.ts", "source_location": "L235"}, {"caller_nid": "services_pdf_service_pdfservice_coercemargin", "callee": "max", "is_member_call": true, "source_file": "D:\\Codes\\image2pdf\\src\\app\\services\\pdf.service.ts", "source_location": "L235"}, {"caller_nid": "services_pdf_service_pdfservice_coercehexcolor", "callee": "test", "is_member_call": true, "source_file": "D:\\Codes\\image2pdf\\src\\app\\services\\pdf.service.ts", "source_location": "L239"}, {"caller_nid": "services_pdf_service_pdfservice_fillpagebackground", "callee": "setFillColor", "is_member_call": true, "source_file": "D:\\Codes\\image2pdf\\src\\app\\services\\pdf.service.ts", "source_location": "L243"}, {"caller_nid": "services_pdf_service_pdfservice_fillpagebackground", "callee": "rect", "is_member_call": true, "source_file": "D:\\Codes\\image2pdf\\src\\app\\services\\pdf.service.ts", "source_location": "L244"}, {"caller_nid": "services_pdf_service_pdfservice_addimagetocell", "callee": "addImage", "is_member_call": false, "source_file": "D:\\Codes\\image2pdf\\src\\app\\services\\pdf.service.ts", "source_location": "L270"}, {"caller_nid": "services_pdf_service_pdfservice_addimagetocell", "callee": "saveGraphicsState", "is_member_call": true, "source_file": "D:\\Codes\\image2pdf\\src\\app\\services\\pdf.service.ts", "source_location": "L274"}, {"caller_nid": "services_pdf_service_pdfservice_addimagetocell", "callee": "rect", "is_member_call": true, "source_file": "D:\\Codes\\image2pdf\\src\\app\\services\\pdf.service.ts", "source_location": "L275"}, {"caller_nid": "services_pdf_service_pdfservice_addimagetocell", "callee": "clip", "is_member_call": true, "source_file": "D:\\Codes\\image2pdf\\src\\app\\services\\pdf.service.ts", "source_location": "L276"}, {"caller_nid": "services_pdf_service_pdfservice_addimagetocell", "callee": "discardPath", "is_member_call": true, "source_file": "D:\\Codes\\image2pdf\\src\\app\\services\\pdf.service.ts", "source_location": "L277"}, {"caller_nid": "services_pdf_service_pdfservice_addimagetocell", "callee": "addImage", "is_member_call": false, "source_file": "D:\\Codes\\image2pdf\\src\\app\\services\\pdf.service.ts", "source_location": "L278"}, {"caller_nid": "services_pdf_service_pdfservice_addimagetocell", "callee": "restoreGraphicsState", "is_member_call": true, "source_file": "D:\\Codes\\image2pdf\\src\\app\\services\\pdf.service.ts", "source_location": "L279"}]}